Oasys/REPORTER/__init__.py
Oasys/REPORTER/colour.py
Oasys/REPORTER/core.py
Oasys/REPORTER/funcs.py
Oasys/REPORTER/image.py
Oasys/REPORTER/item.py
Oasys/REPORTER/itemobject.py
Oasys/REPORTER/options.py
Oasys/REPORTER/page.py
Oasys/REPORTER/reporter.py
Oasys/REPORTER/template.py
Oasys/REPORTER/utils.py
Oasys/REPORTER/variable.py
Oasys/REPORTER/window.py
oasys_reporter-22.1.0.dist-info/licenses/LICENSE
oasys_reporter-22.1.0.dist-info/METADATA
oasys_reporter-22.1.0.dist-info/WHEEL
oasys_reporter-22.1.0.dist-info/top_level.txt
oasys_reporter-22.1.0.dist-info/RECORD
